iamend_theo/__init__.py
iamend_theo/ax.py
iamend_theo/bo.py
iamend_theo/theo.py
iamend_theo-0.0.2.dist-info/LICENSE
iamend_theo-0.0.2.dist-info/METADATA
iamend_theo-0.0.2.dist-info/WHEEL
iamend_theo-0.0.2.dist-info/top_level.txt
iamend_theo-0.0.2.dist-info/RECORD
