Metadata-Version: 2.1
Name: iamend_theo
Version: 0.0.2
Summary: A small example package of functions for eddy current problems
Home-page: https://github.com/carabedo/iamend_theo
Author: carabedo
Author-email: fcarabedo@cnea.gov.ar
License: UNKNOWN
Project-URL: Bug Tracker, https://github.com/carabedo/iamend_theo/issues
Platform: UNKNOWN
Classifier: Programming Language :: Python :: 3
Classifier: License :: OSI Approved :: MIT License
Classifier: Operating System :: OS Independent
Requires-Python: >=3.6
License-File: LICENSE
